{
  "post_id": 1927,
  "title": "Mẹ Chồng Gọi Tôi Là Người Ngoài, Sổ Đỏ Biệt Thự Gò Vấp 5 Tỷ Khiến Cả Mâm Giỗ Câm Lặng",
  "focus_keyword": "biệt thự Gò Vấp, lật kèo pháp lý",
  "seo_title": "Chuyện lật kèo pháp lý tại biệt thự Gò Vấp",
  "seo_description": "Một câu chuyện kịch tính về lật kèo pháp lý tại biệt thự Gò Vấp với những cú vả mặt không thể nào quên.",
  "intro": "<p>Trong mâm giỗ ba chồng, tôi bị mẹ chồng chỉ thẳng mặt gọi là người ngoài và bắt dọn khỏi căn biệt thự Gò Vấp sau bốn năm nhẫn nhịn.</p>\n<p>Chị chồng cười nhạo tôi dân tỉnh, chồng cúi đầu không nói, còn họ hàng xúm vào ép tôi ký giấy từ bỏ mọi quyền lợi.</p>\n<p>Tôi lau tay, mở túi lấy bản sao công chứng sổ đỏ đứng tên riêng mình cùng sao kê 4,8 tỷ tiền mua nhà trước hôn nhân.</p>\n<p>Khi cán bộ công chứng bước vào cửa, cả mâm giỗ mới hiểu người họ muốn đuổi đi chính là chủ thật của căn biệt thự.</p>",
  "chapters": [
    {
      "title": "Chương 1: Mâm Giỗ Và Câu Nói Người Ngoài",
      "content": "<p>Mâm cơm giỗ ba chồng bày biện trang trọng, nhưng không khí lại nặng nề như thể có một tảng đá lớn đè lên lòng tôi.</p>\n<p>Những ánh mắt châm biếm từ gia đình chồng như những mũi dao sắc nhọn, chĩa thẳng vào tôi, khiến tôi cảm thấy mình như một kẻ tội đồ bị đưa ra xét xử.</p>\n<p>Mẹ chồng tôi, người phụ nữ luôn tự hào về phẩm giá và gia đình, giờ đây lại lạnh lùng chỉ trích tôi, gọi tôi là “người ngoài” trước mặt họ hàng.</p>\n<p>Từng từ mà bà thốt ra như những viên đạn bắn thẳng vào trái tim tôi, khiến tôi cảm thấy bị đẩy vào góc tường, không còn đường lui.</p>\n<p>Chồng tôi, Nguyễn Hoàng, chỉ biết cúi đầu, ánh mắt lạc lõng như một chiếc thuyền giữa dòng nước cuồn cuộn, không dám lên tiếng bảo vệ vợ.</p>\n<p>Hình ảnh đó như một nhát dao cứa vào lòng tôi, khiến tôi cảm thấy như mọi hy vọng đều tan biến.</p>\n<p>Nhưng họ không biết, căn biệt thự ba tầng mặt tiền Gò Vấp trị giá hơn 5 tỷ đồng đang nằm gọn trong tay tôi, là tài sản riêng mà tôi đã vất vả tích lũy.</p>\n<p>Cuộc chiến pháp lý để khẳng định quyền sở hữu bắt đầu ngay hôm đó, và tôi sẽ không để họ dẫm đạp lên danh dự của mình thêm một lần nào nữa.</p>\n<p>Tôi nhìn quanh mâm cơm, những món ăn đều được bày biện đẹp mắt, nhưng không thể nào nuốt nổi dù chỉ một miếng.</p>\n<p>Các cô, các dì của chồng tôi thì thầm với nhau, ánh mắt đầy vẻ thương hại khi nhìn về phía tôi, như thể đang bàn tán về một kẻ thất bại.</p>\n<p>Tôi cảm thấy khó chịu, như thể có một cái gì đó nghẹn lại nơi cổ họng, không thể thốt ra lời nào.</p>\n<p>Ngồi bên cạnh, chồng tôi vẫn giữ im lặng, không một lời an ủi hay động viên, khiến tôi càng thêm thất vọng.</p>\n<p>Tôi đã từng nghĩ rằng cuộc sống hôn nhân sẽ mang lại cho tôi niềm hạnh phúc, nhưng giờ đây, tôi chỉ cảm thấy đơn độc.</p>\n<p>Thời gian trôi chậm chạp, như thể mỗi giây đều kéo dài đến vô tận.</p>\n<p>Khi bữa tiệc đến phần kết thúc, mẹ chồng tôi đứng dậy, giọng nói đầy uy quyền: “Vân, con không phải là thành viên của gia đình này.</p>\n<p>Con phải nhớ điều đó.”</p>\n<p>Câu nói ấy như một cái tát nảy lửa, khiến tôi không thể chịu đựng thêm nữa.</p>\n<p>Trong lòng tôi bùng lên một ngọn lửa, một quyết tâm mãnh liệt: Tôi sẽ không để mình bị xem thường như vậy.</p>\n<p>Tôi đã chịu đựng đủ rồi, đến lúc phải đứng lên và bảo vệ quyền lợi của bản thân.</p>\n<p>Ngay khi vừa rời khỏi bữa tiệc, tôi đã bắt đầu lên kế hoạch cho cuộc chiến pháp lý mà tôi biết sẽ không hề đơn giản.</p>\n<p>Tôi sẽ yêu cầu chồng ký hợp đồng chuyển nhượng quyền sở hữu biệt thự, và tôi sẽ chứng minh tài sản đó thuộc về tôi.</p>\n<p>Ý nghĩ về việc có trong tay bản sao kê tài khoản ngân hàng Việt Thương Bank, với số dư 5 tỷ VNĐ, khiến tôi cảm thấy tự tin hơn.</p>\n<p>Tôi đã chuẩn bị sẵn sàng cho cuộc chiến này, và không ai có thể ngăn cản tôi.</p>\n<p>Trái tim tôi như đang đập loạn xạ, nhưng bên trong lại tràn đầy lý trí và quyết tâm.</p>\n<p>Tôi biết rằng trong 24 giờ tới, phải chứng minh quyền sở hữu của mình trước khi mẹ chồng có thể can thiệp và làm giả giấy tờ.</p>\n<p>Không còn thời gian để do dự hay sợ hãi, tôi phải hành động ngay lập tức.</p>\n<p>Với từng bước chân dứt khoát, tôi rời khỏi biệt thự, lòng đầy quyết tâm và lý trí.</p>\n<p>Cái ánh mắt châm biếm của gia đình chồng sẽ không còn là nỗi lo của tôi nữa.</p>\n<p>Tôi sẽ không để họ dẫm đạp lên danh dự của tôi thêm một lần nào nữa.</p>"
    },
    {
      "title": "Chương 2: Tờ Giấy Ép Ký Rời Khỏi Biệt Thự",
      "content": "<p>Tôi ngồi một mình trong căn phòng nhỏ, ánh đèn vàng ấm áp hắt lên những món đồ nội thất giản dị.</p>\n<p>Những ký ức về quá trình mua căn biệt thự Gò Vấp lại ùa về, như một bộ phim quay chậm, đè nặng lên tâm trí tôi.</p>\n<p>Đó là một buổi chiều tháng năm oi ả, khi tôi lần đầu tiên đặt chân đến căn biệt thự mà tôi đã mơ ước.</p>\n<p>Căn biệt thự ba tầng, với thiết kế hiện đại, nằm ở một vị trí đắc địa, khiến trái tim tôi đập rộn ràng.</p>\n<p>Tôi đã phải làm việc không ngừng nghỉ, từ những ngày đầu ra trường, để có đủ tiền cho cuộc sống và giấc mơ của riêng mình.</p>\n<p>Những giờ làm thêm tại quán cà phê, những tháng ngày chăm chỉ làm việc tại công ty, tất cả đều hướng đến một mục tiêu duy nhất: sở hữu căn nhà của chính mình.</p>\n<p>Giá trị căn biệt thự lên tới 5 tỷ đồng, một con số không hề nhỏ đối với một người như tôi.</p>\n<p>Tôi đã dành dụm từng đồng, từng đồng một, từ những khoản lương ít ỏi.</p>\n<p>Cảm giác ngồi trong phòng kế hoạch, trước mặt là hợp đồng chuyển nhượng, tim tôi đập mạnh vì sự háo hức.</p>\n<p>Nhưng không chỉ có tiền, tôi còn cần sự kiên nhẫn và quyết tâm.</p>\n<p>Từng bước, từng bước, tôi đã phải vượt qua không ít khó khăn để có thể có được chữ ký của chủ sở hữu cũ.</p>\n<p>Những cuộc thương lượng căng thẳng với họ, những đêm không ngủ suy nghĩ về từng chi tiết trong hợp đồng, và nhất là sự hoài nghi từ những người xung quanh.</p>\n<p>Tôi nhớ rõ ánh mắt của anh chủ cũ, khi ông ta chỉ trích khả năng tài chính của tôi.</p>\n<p>“Cô có chắc mình có đủ khả năng để duy trì căn biệt thự này không?” ông ta hỏi, giọng điệu đầy nghi ngờ.</p>\n<p>Nhưng tôi không thể để những lời nói ấy làm mình chùn bước.</p>\n<p>Tôi đã đứng thẳng lưng, nhìn thẳng vào mắt ông ta, nói với sự kiên định: “Tôi sẽ chứng minh cho ông thấy, tôi có thể, và tôi sẽ làm được.”</p>\n<p>Cuối cùng, sau nhiều lần họp mặt, tôi đã có được hợp đồng chuyển nhượng, với chữ ký của chủ sở hữu cũ.</p>\n<p>Nhưng không dừng lại ở đó, tôi biết rằng, để bảo vệ quyền lợi của mình, tôi cần phải có thêm bằng chứng.</p>\n<p>Tôi đã quyết định đến ngân hàng Việt Thương Bank, nơi mà tôi gửi tiết kiệm qua nhiều năm.</p>\n<p>Đứng trước quầy giao dịch, tôi yêu cầu nhân viên in sao kê tài khoản ngân hàng của mình.</p>\n<p>“Xin chào, tôi muốn in sao kê tài khoản, vui lòng giúp tôi!” tôi đã nói với giọng tự tin.</p>\n<p>Chờ đợi trong sự hồi hộp, những tờ giấy in ra, với con số 5 tỷ đồng rõ ràng hiện lên trước mắt tôi.</p>\n<p>Cảm giác như một cơn gió mới thổi qua, làm tôi thấy vững tâm hơn bao giờ hết.</p>\n<p>Giờ đây, tôi không chỉ có hợp đồng chuyển nhượng, mà còn có sao kê tài khoản, là bằng chứng cho quyền sở hữu của mình.</p>\n<p>Nhưng trong lòng tôi vẫn lo lắng, không chỉ vì sự nghi ngờ của gia đình chồng, mà còn bởi mẹ chồng vốn nổi tiếng khôn khéo, có thể làm mọi thứ để chiếm đoạt tài sản.</p>\n<p>Tôi biết rằng, trong vòng 24 giờ tới, tôi sẽ phải chứng minh quyền sở hữu của căn biệt thự, trước khi bà có thể làm điều gì đó để phá hoại mọi thứ.</p>\n<p>Cảm giác chờ đợi như ngàn cân treo trên sợi tóc, tôi tự nhủ rằng mình không thể để nỗi sợ hãi xâm chiếm.</p>\n<p>Tôi đã quyết định bước ra khỏi cái bóng của người “ngoài cuộc”, và trở thành chủ nhân thực sự của căn biệt thự này.</p>\n<p>Với tâm trí quyết tâm, tôi tìm thấy sức mạnh từ những khó khăn đã trải qua để có được nó.</p>\n<p>Căn biệt thự không chỉ là nơi ở, mà còn là biểu tượng cho sự nỗ lực và khát vọng không bao giờ tắt của tôi.</p>\n<p>Và giờ đây, tôi sẽ không để ai dẫm đạp lên nó.</p>"
    },
    {
      "title": "Chương 3: Người Chồng Cúi Đầu Giữa Họ Hàng",
      "content": "<p>Buổi sáng hôm sau, ánh nắng len lỏi qua những tán cây xanh rì ngoài cửa sổ, nhuộm vàng cả không gian trong căn biệt thự Gò Vấp.</p>\n<p>Tôi ngồi trong bếp, tay khuấy nhẹ nồi cháo gà đang sôi ùng ục, nhưng tâm trí tôi không thể nào tập trung vào món ăn.</p>\n<p>Những câu nói của mẹ chồng đêm qua cứ lặp đi lặp lại trong đầu tôi như một bản nhạc buồn không có hồi kết.</p>\n<p>Cảm giác bị châm biếm, bị coi thường khiến trái tim tôi như bị bóp nghẹt.</p>\n<p>Trong lúc tôi đang mải mê suy nghĩ, bỗng nghe thấy tiếng thì thầm từ phòng khách vọng lại.</p>\n<p>Tôi khẽ nghiêng tai, cố gắng lắng nghe.</p>\n<p>Giọng nói của mẹ chồng vang lên, lạnh lùng và sắc bén: \"Chúng ta không thể để con bé đó giữ chặt biệt thự này!\"</p>\n<p>Chị chồng tôi, Nga, đáp lại bằng giọng điệu đầy ngạo mạn: \"Mẹ yên tâm, con đã có kế hoạch.</p>\n<p>Để con và mẹ cùng bàn bạc chi tiết.\"</p>\n<p>Như bị thôi miên, tôi lén lút tiến lại gần cửa phòng khách, nơi mà ánh sáng le lói từ bên trong chiếu ra.</p>\n<p>Trong khoảnh khắc đó, tôi cảm nhận được một cơn gió lạnh chạy dọc sống lưng.</p>\n<p>Họ đang bàn về tôi, về căn biệt thự mà tôi đã dày công gìn giữ.</p>\n<p>\"Con bé đó không xứng đáng với bất cứ thứ gì trong gia đình này,\" mẹ chồng tôi tiếp tục, giọng nói đầy căm ghét.</p>\n<p>\"Mẹ cứ yên tâm, con sẽ giả mạo giấy tờ, sẽ có một bản hợp đồng chuyển nhượng với chữ ký của nó,\" Nga nói, giọng điệu tự tin đầy khinh miệt.</p>\n<p>Tôi không thể tin vào tai mình, lòng tôi như vỡ vụn khi nghe thấy những âm mưu tồi tệ đang diễn ra trước mắt.</p>\n<p>\"Chúng ta sẽ làm mọi thứ để lấy lại quyền sở hữu, không thể để nó một mình làm chủ biệt thự này,\" mẹ chồng tôi khẳng định, ánh mắt đầy quyết tâm.</p>\n<p>Tôi lùi lại, tim đập thình thịch trong lồng ngực, cảm giác hoảng loạn dâng lên.</p>\n<p>Tôi phải hành động ngay, không thể để họ thực hiện âm mưu này.</p>\n<p>Trong đầu tôi, một kế hoạch đang dần hình thành.</p>\n<p>Tôi quyết định sẽ tìm cách thu thập bằng chứng để bảo vệ quyền sở hữu của mình trước khi mọi thứ trở nên tồi tệ hơn.</p>\n<p>Trở lại bếp, tôi bắt đầu soạn lại tất cả các chứng từ liên quan đến căn biệt thự.</p>\n<p>Những giấy tờ chuyển nhượng, chứng minh tài sản, và bản sao kê tài khoản ngân hàng Việt Thương Bank của tôi với số dư 5 tỷ VNĐ đều được xếp gọn gàng trên bàn.</p>\n<p>Phải, tôi sẽ chứng minh quyền sở hữu của mình bằng tất cả những gì tôi có.</p>\n<p>Mặc dù lòng đầy lo lắng, nhưng tôi cũng cảm thấy một chút tự tin khi nghĩ đến những bằng chứng pháp lý mà tôi nắm giữ.</p>\n<p>Thời gian không chờ đợi ai, tôi phải hành động nhanh chóng.</p>\n<p>Cuộc chiến pháp lý sẽ diễn ra ngay trong những giờ tới, và tôi cần phải chuẩn bị thật kỹ lưỡng.</p>\n<p>Trong khi tôi đang loay hoay với những tài liệu, một ý nghĩ chợt lóe lên trong đầu: \"Có thể tôi cần làm một bản sao tài liệu quan trọng này để bảo vệ mình hơn nữa.\"</p>\n<p>Tôi vội vàng lấy điện thoại và lên mạng tìm kiếm thông tin về các dịch vụ sao chép tài liệu uy tín gần đây.</p>\n<p>Khi đang tìm kiếm, tôi bỗng nhớ đến một người bạn thân tên Minh, là luật sư có tiếng ở thành phố.</p>\n<p>Minh từng giúp tôi trong một số vụ việc pháp lý trước đây, và tôi rất tin tưởng vào khả năng của anh.</p>\n<p>Quyết định gọi cho Minh, tôi nhanh chóng nhập số điện thoại và nhấn gọi.</p>\n<p>Tiếng chuông reo vang, lòng tôi hồi hộp không thể tả.</p>\n<p>\"A lô, Vân à?</p>\n<p>Có chuyện gì gấp không?\" Giọng của Minh vang lên, đầy lo lắng.</p>\n<p>\"Minh, mình cần sự giúp đỡ của cậu ngay bây giờ!\" Tôi nói, giọng điệu hốt hoảng.</p>\n<p>\"Chuyện gì vậy?\" Minh hỏi, vẻ nghiêm túc hiện rõ trên gương mặt anh.</p>\n<p>Tôi nhanh chóng thuật lại tình hình, từ buổi giỗ cho đến âm mưu của mẹ chồng và chị chồng tôi.</p>\n<p>\"Cậu phải giúp mình thu thập tất cả bằng chứng để chứng minh quyền sở hữu biệt thự này!\" Tôi nói, giọng đầy quyết tâm.</p>\n<p>\"Được rồi, mình sẽ đến ngay,\" Minh đáp, giọng điệu nghiêm túc.</p>\n<p>Cuộc gọi kết thúc, và tôi cảm thấy một chút yên tâm.</p>\n<p>Dù mâu thuẫn còn đang chực chờ, nhưng tôi biết rằng mình không đơn độc trong cuộc chiến này.</p>\n<p>Giờ đây, tôi cần phải chuẩn bị tốt nhất cho cuộc đối đầu với mẹ chồng và chị chồng.</p>\n<p>Thời gian không còn nhiều, và tôi phải hành động ngay lập tức.</p>\n<p>Mọi thứ sẽ thay đổi trong vòng 24 giờ tới, và tôi sẽ không để cho bất kỳ ai dẫm đạp lên danh dự của mình thêm lần nào nữa.</p>"
    },
    {
      "title": "Chương 4: Sổ Đỏ Gò Vấp Trong Túi Xách Cũ",
      "content": "<p>Lê Vân đứng giữa phòng khách rộng lớn của căn biệt thự, nơi mà cô đã từng mơ ước có được.</p>\n<p>Từng bức tranh treo trên tường, từng món đồ nội thất sang trọng đều gợi nhớ về những kỷ niệm ngọt ngào đã qua.</p>\n<p>Nhưng giờ đây, tất cả những điều đó lại trở thành gánh nặng, một áp lực khổng lồ đè nặng lên đôi vai mảnh mai của cô.</p>\n<p>Ngọn đèn chùm rực rỡ trên trần nhà tỏa ánh sáng vàng ấm, nhưng nó không thể xua tan đi cái lạnh lẽo trong lòng Lê Vân.</p>\n<p>Ngón tay cô lướt nhẹ trên bàn phím laptop, gõ từng chữ để chuẩn bị cho cuộc chiến pháp lý sắp tới.</p>\n<p>Trong đầu cô, từng câu chữ hiện lên rõ rệt, như một bản kế hoạch chi tiết cho ngày mai.</p>\n<p>Đầu tiên, cô cần phải thu thập tất cả các tài liệu liên quan đến quyền sở hữu căn biệt thự này.</p>\n<p>Tim cô đập loạn nhịp khi nghĩ đến việc phải đối mặt với mẹ chồng, người mà cô biết sẽ không từ thủ đoạn nào để chiếm đoạt tài sản.</p>\n<p>Nhưng Lê Vân không thể cho phép bản thân gục ngã, cô đã quyết tâm và sẽ không để cho bất kỳ ai dẫm đạp lên danh dự của mình.</p>\n<p>Đầu tiên, cô mở ngăn kéo bàn làm việc và lôi ra một tập tài liệu dày cộp, đó là hợp đồng chuyển nhượng quyền sở hữu căn biệt thự.</p>\n<p>Nhìn vào chữ ký của mình trên tờ giấy trắng, cô cảm thấy một niềm tin trỗi dậy.</p>\n<p>Cô đã bỏ ra rất nhiều công sức, tiền bạc để mua căn biệt thự này, và không ai có quyền tước đoạt nó khỏi tay cô.</p>\n<p>Cô không thể để cho mẹ chồng với những ánh mắt châm biếm, châm chọc, có thể lật ngược tình thế.</p>\n<p>Giờ đây, mọi thứ phụ thuộc vào việc cô có thể chứng minh quyền sở hữu của mình hay không.</p>\n<p>Thời gian không chờ đợi ai, chỉ còn chưa đầy 24 giờ nữa là đến cuộc họp với gia đình chồng.</p>\n<p>Cô cần phải tìm một luật sư có kinh nghiệm, người có thể giúp cô vạch ra kế hoạch cụ thể để bảo vệ quyền lợi của mình.</p>\n<p>Vân quyết định lấy điện thoại, bấm số liên lạc của một luật sư mà cô đã tìm hiểu trước đó.</p>\n<p>Mỗi giây trôi qua đều như một thử thách, cô cảm nhận được áp lực đè nặng lên vai mình.</p>\n<p>Khi đầu dây bên kia cất lên giọng nói trầm ấm, Lê Vân cảm thấy một chút yên lòng.</p>\n<p>“Xin chào, tôi là Lê Vân, tôi cần sự tư vấn của anh về một vấn đề khẩn cấp,” cô nói với giọng điệu đầy quyết tâm.</p>\n<p>Luật sư đã lắng nghe và hẹn gặp cô tại một quán cà phê gần đó để thảo luận chi tiết hơn về tình hình.</p>\n<p>Cô cảm thấy một tia hy vọng le lói, nhưng lòng vẫn còn nặng trĩu.</p>\n<p>Trước khi rời khỏi nhà, Vân quyết định kiểm tra lại tập tài liệu một lần nữa.</p>\n<p>Cô lôi ra bản sao kê tài khoản ngân hàng Việt Thương Bank, nơi mà số tiền 5 tỷ VNĐ đang được gửi giữ, tất cả đều được thể hiện rõ ràng.</p>\n<p>Những con số trên bản sao kê như một lời khẳng định chắc chắn rằng căn biệt thự này thuộc về cô.</p>\n<p>Cô tự nhủ: “Không ai có thể lật đổ sự thật này.”</p>\n<p>Trên đường đi đến quán cà phê, lòng cô đầy những lo lắng và hồi hộp.</p>\n<p>Cô không thể không nghĩ đến những gì mẹ chồng có thể làm để ngăn cản cô.</p>\n<p>Cái nhìn châm biếm của bà vẫn còn văng vẳng bên tai, và điều đó càng thôi thúc cô phải chiến đấu.</p>\n<p>Quán cà phê nhỏ nằm ở góc phố quen thuộc, không khí bên trong ấm áp, nhưng lòng cô vẫn cảm thấy lạnh lẽo.</p>\n<p>Cô chọn một góc khuất, nơi mà không ai có thể nghe thấy cuộc trò chuyện của họ.</p>\n<p>Chỉ một lát sau, luật sư bước vào, dáng người cao ráo, với bộ vest lịch lãm.</p>\n<p>Ông mỉm cười chào cô, nhưng ánh mắt nghiêm túc của ông ngay lập tức khiến Vân cảm thấy không thể chủ quan.</p>\n<p>“Cô Lê Vân, tôi đã nghe qua tình hình của cô,” ông nói với giọng điềm tĩnh, nhưng Vân cảm nhận được sự căng thẳng trong không khí.</p>\n<p>“Tôi cần một kế hoạch rõ ràng để bảo vệ quyền sở hữu căn biệt thự này,” cô nói, không để cho bất kỳ sự nghi ngờ nào xuất hiện.</p>\n<p>Luật sư gật đầu, bắt đầu nói về các bước cần thực hiện.</p>\n<p>“Đầu tiên, cô cần phải thu thập tất cả các tài liệu chứng minh quyền sở hữu,” ông nói, ánh mắt chăm chú nhìn vào cô.</p>\n<p>“Chúng ta cần bản sao kê tài khoản ngân hàng, hợp đồng chuyển nhượng, và nếu có thể, hãy tìm những nhân chứng đã ký vào hợp đồng.”</p>\n<p>Vân gật đầu, từng câu nói của ông như một ngọn đèn soi đường cho cô trong bóng tối.</p>\n<p>“Tôi cũng sẽ giúp cô soạn thảo một văn bản chính thức để gửi đến gia đình chồng, nhấn mạnh quyền lợi của cô,” ông tiếp tục.</p>\n<p>Cảm giác như những mảnh ghép đang dần dần được lắp ráp lại, Vân cảm thấy tâm lý của mình trở nên vững vàng hơn.</p>\n<p>“Cảm ơn anh vì đã giúp tôi,” cô nói, lòng tràn đầy quyết tâm.</p>\n<p>Khi cuộc họp kết thúc, Lê Vân đứng dậy, nhìn thẳng vào mắt luật sư, “Tôi sẽ không để cho họ dẫm đạp lên tôi một lần nào nữa.”</p>\n<p>Luật sư cười nhẹ, “Tôi tin rằng cô sẽ làm được.”</p>\n<p>Điều này như một lời hứa, và Vân cảm thấy như mình đã khơi dậy được sức mạnh bên trong.</p>\n<p>Giờ đây, cô cần phải chuẩn bị cho cuộc chiến sắp tới, không chỉ vì bản thân mình mà còn vì danh dự của gia đình.</p>\n<p>Trở về nhà, Vân không thể ngừng suy nghĩ về những bước tiếp theo.</p>\n<p>Cô sẽ phải đối mặt với mẹ chồng, nhưng giờ đây, cô đã có vũ khí trong tay.</p>\n<p>Không còn là cô gái yếu đuối trước kia, mà đã trở thành một người phụ nữ mạnh mẽ, quyết tâm bảo vệ những gì thuộc về mình.</p>\n<p>Cuộc chiến pháp lý này không chỉ là về tài sản, mà còn là về lòng tự trọng, danh dự và quyền lực của một người phụ nữ.</p>\n<p>Và Lê Vân sẵn sàng cho mọi thứ.</p>"
    },
    {
      "title": "Chương 5: Sao Kê 4,8 Tỷ Trước Ngày Cưới",
      "content": "<p>Ánh nắng chói chang xuyên qua khung cửa sổ của căn phòng nhỏ, nhưng lòng tôi vẫn tối tăm như bầu trời u ám bên ngoài.</p>\n<p>Ngồi giữa mâm cơm giỗ ba chồng, tôi cảm thấy như mình là một kẻ ngoại đạo, lạc lõng giữa những cái nhìn đầy châm biếm và khinh miệt từ gia đình chồng.</p>\n<p>Mẹ chồng, với gương mặt lạnh lùng, không ngừng chỉ trích tôi, gọi tôi là 'người ngoài' trước mặt họ hàng.</p>\n<p>Những lời nói đó như những mũi dao sắc nhọn đâm vào lòng tự trọng của tôi, khiến tôi cảm thấy bị đẩy vào một góc tường không lối thoát.</p>\n<p>Chồng tôi, người mà tôi luôn nghĩ sẽ đứng về phía tôi trong những lúc khó khăn, giờ đây chỉ biết cúi đầu, không dám lên tiếng.</p>\n<p>Lòng tôi như bị cắt xé bởi nỗi đau không thể diễn tả bằng lời.</p>\n<p>Nhưng họ không biết, căn biệt thự ba tầng mặt tiền Gò Vấp trị giá hơn 5 tỷ đồng đang là tài sản riêng của tôi.</p>\n<p>Cuộc chiến pháp lý để khẳng định quyền sở hữu bắt đầu ngay hôm đó, và tôi sẽ không để họ dẫm đạp lên danh dự của mình thêm một lần nào nữa.</p>\n<p>Thời gian trôi qua, áp lực từ gia đình chồng ngày càng gia tăng, như những cơn sóng dữ vỗ vào bờ đá, không ngừng cuốn trôi mọi thứ.</p>\n<p>Tôi cảm thấy căng thẳng, mỗi giây phút trôi qua đều như một thách thức lớn lao, nhưng quyết tâm không bỏ cuộc vẫn cháy bỏng trong lòng tôi.</p>\n<p>Trở về nhà sau bữa tiệc giỗ, tôi ngồi lặng lẽ trong góc phòng, nhìn ra ngoài cửa sổ nơi những chiếc lá rơi lả tả, như những giọt nước mắt của tôi.</p>\n<p>Trong đầu tôi, những ý tưởng về việc lấy lại quyền sở hữu căn biệt thự bắt đầu hình thành.</p>\n<p>Tôi phải có một kế hoạch cụ thể, một chiến lược rõ ràng để chứng minh quyền sở hữu của mình.</p>\n<p>Đầu tiên, tôi cần lấy bản sao kê tài khoản ngân hàng tại Việt Thương Bank, nơi có số dư 5 tỷ VNĐ mà tôi đã tích lũy từ những năm tháng miệt mài làm việc của mình.</p>\n<p>Đó sẽ là bằng chứng không thể chối cãi về quyền sở hữu của tôi đối với căn biệt thự.</p>\n<p>Nhưng tôi biết rằng, mẹ chồng sẽ không dễ dàng để tôi thực hiện điều này.</p>\n<p>Bà ấy là một người phụ nữ từng trải, thông minh và nham hiểm.</p>\n<p>Tôi cần phải nhanh chóng hành động trước khi bà ấy kịp nhận ra kế hoạch của tôi.</p>\n<p>Đêm hôm đó, khi mọi người đã chìm vào giấc ngủ, tôi lén lút vào phòng làm việc của chồng.</p>\n<p>Những ngón tay tôi run rẩy khi tìm kiếm hợp đồng chuyển nhượng quyền sở hữu căn biệt thự, một tài liệu quan trọng có chữ ký số CA mà tôi cần phải bảo vệ.</p>\n<p>Trong ánh đèn mờ ảo, tôi lục lọi từng ngăn kéo, từng tài liệu, cho đến khi ánh mắt tôi dừng lại ở một tệp hồ sơ dày cộp được cất gọn gàng.</p>\n<p>Nhẹ nhàng mở ra, tôi thấy hợp đồng mà tôi đã ký trước đó, một bản sao kê tài khoản ngân hàng và biên bản niêm phong từ cơ quan điều tra.</p>\n<p>Những bằng chứng này sẽ giúp tôi đứng vững trong cuộc chiến pháp lý sắp tới.</p>\n<p>Nhưng tôi biết rằng, việc tìm được bằng chứng là một chuyện, nhưng việc bảo vệ chúng trước sự can thiệp của mẹ chồng lại là một vấn đề khác.</p>\n<p>Tôi quyết định sẽ không để mẹ chồng có cơ hội làm giả giấy tờ hay chiếm đoạt tài sản một lần nào nữa.</p>\n<p>Cuộc chiến này không chỉ là về tiền bạc, mà còn là về danh dự, sự công bằng và quyền lợi của chính bản thân tôi.</p>\n<p>Sáng hôm sau, khi ánh nắng vừa ló dạng, tôi đã có mặt tại ngân hàng Việt Thương Bank để yêu cầu sao kê tài khoản.</p>\n<p>Nhân viên ngân hàng nhìn tôi với ánh mắt tò mò, nhưng tôi không quan tâm đến điều đó.</p>\n<p>Tôi cần phải có những gì mình cần, và tôi sẽ không để ai ngăn cản mình.</p>\n<p>Vài phút sau, tôi đã có trong tay bản sao kê tài khoản ngân hàng, với số dư 5 tỷ VNĐ hiện rõ trên đó.</p>\n<p>Nhìn vào con số ấy, lòng tôi như được tiếp thêm sức mạnh.</p>\n<p>Đây sẽ là vũ khí của tôi trong cuộc chiến này.</p>\n<p>Trở về nhà, tôi sắp xếp lại những tài liệu, chuẩn bị cho cuộc đối đầu không thể tránh khỏi với mẹ chồng.</p>\n<p>Đã đến lúc tôi phải đứng lên, không chỉ vì bản thân mình mà còn vì những gì tôi xứng đáng có được.</p>\n<p>Tôi sẽ không để họ tiếp tục khinh miệt và dẫm đạp lên tôi.</p>\n<p>Cuộc chiến pháp lý của tôi sẽ bắt đầu từ đây, và tôi sẽ chứng minh cho họ thấy rằng, tôi không phải là một người ngoài, mà là chủ nhân thực sự của căn biệt thự Gò Vấp.</p>"
    },
    {
      "title": "Chương 6: Cán Bộ Công Chứng Bước Vào Mâm Giỗ",
      "content": "<p>Đêm đã buông xuống, không khí trong nhà vẫn tĩnh lặng nhưng nặng nề như một bầu trời u ám.</p>\n<p>Tôi ngồi trên chiếc ghế sofa da màu nâu sẫm, đôi tay buông thõng, tâm trí rối bời với những gì vừa diễn ra trong bữa cơm giỗ.</p>\n<p>Những câu nói châm biếm của mẹ chồng vẫn văng vẳng bên tai, từng chữ như những nhát dao sắc bén đâm vào trái tim tôi.</p>\n<p>Người ta có thể dễ dàng nhận ra sự lạnh lùng của bà, nhưng không ai biết rằng bên trong đó là một âm mưu đang chờ cơ hội bùng nổ.</p>\n<p>Tôi rời khỏi ghế, bước vào phòng làm việc của chồng, nơi chứa đựng biết bao kỷ niệm giữa hai chúng tôi.</p>\n<p>Trên bàn, một chiếc laptop còn sáng đèn, ánh sáng nhấp nháy phản chiếu lên bức tường trắng.</p>\n<p>Tôi mở máy, và một cảm giác lo lắng trỗi dậy khi nghĩ đến khả năng mẹ chồng có thể làm giả giấy tờ để chiếm đoạt biệt thự.</p>\n<p>Đầu óc tôi bắt đầu quay cuồng với hàng loạt ý tưởng, và tôi quyết định cần phải hành động ngay lập tức.</p>\n<p>Nhìn vào màn hình, một bức thư điện tử từ ngân hàng Việt Thương Bank hiện ra trong hộp thư đến, khiến tim tôi đập nhanh hơn.</p>\n<p>Tôi mở thư và thấy thông tin về số dư tài khoản của mình: 5 tỷ VNĐ.</p>\n<p>Chỉ cần bản sao kê tài khoản này, tôi có thể chứng minh quyền sở hữu căn biệt thự.</p>\n<p>Nhưng tôi cần thêm chứng cứ mạnh mẽ hơn nữa.</p>\n<p>Tôi nhanh chóng gọi điện cho người bạn thân thiết là một luật sư, chị Minh, để nhờ cô giúp đỡ.</p>\n<p>“Chị Minh, em cần chị giúp em thu thập chứng cứ về quyền sở hữu căn biệt thự Gò Vấp,” tôi nói, giọng nén lại vì lo lắng.</p>\n<p>“Có chuyện gì vậy, Vân?” chị hỏi, giọng điệu đầy quan tâm.</p>\n<p>“Mẹ chồng em có thể đang âm thầm chuẩn bị làm giả giấy tờ để chiếm đoạt tài sản,” tôi đáp, cảm giác sợ hãi dâng lên trong lòng.</p>\n<p>“Đừng lo, em sẽ có những gì em cần,” chị Minh trấn an.</p>\n<p>Tôi cúp máy và ngồi lại trên ghế, cảm giác như có một gánh nặng được trút bỏ.</p>\n<p>Nhưng tôi biết, thời gian không chờ đợi ai, và tôi phải nhanh chóng hành động.</p>\n<p>Tôi lục tung những tài liệu cũ trong ngăn kéo bàn, những giấy tờ liên quan đến căn biệt thự mà tôi đã ký kết cách đây vài tháng.</p>\n<p>Trong khi tìm kiếm, những kỷ niệm về quá trình mua bán căn biệt thự, sự vui vẻ khi tôi và chồng cùng nhau trang trí từng góc nhỏ lại hiện về trong tâm trí.</p>\n<p>Cuối cùng, tôi tìm thấy bản hợp đồng chuyển nhượng đứng tên riêng, có chữ ký số CA.</p>\n<p>Đó là một bằng chứng quan trọng có thể giúp tôi khẳng định quyền sở hữu của mình.</p>\n<p>Tôi không thể để mẹ chồng dẫm đạp lên danh dự của mình thêm một lần nào nữa.</p>\n<p>Với bản hợp đồng trong tay, tôi lại mở laptop, đăng nhập vào tài khoản ngân hàng của mình.</p>\n<p>Mọi thông tin hiện ra rõ ràng, và tôi nhanh chóng chụp màn hình lại làm bằng chứng.</p>\n<p>Phải nhanh chóng lấy số dư tài khoản và hợp đồng chuyển nhượng để gửi cho chị Minh.</p>\n<p>Nhưng rồi, một ý nghĩ chợt lóe lên trong đầu tôi: Nếu mẹ chồng thực sự làm giả giấy tờ, liệu bà có thể làm gì với thông tin mà tôi có?</p>\n<p>Tôi quyết định cần phải hành động cẩn thận hơn nữa.</p>\n<p>Tôi khóa laptop lại, đứng dậy và đi ra ngoài, quyết tâm tìm bằng chứng mà tôi cần.</p>\n<p>Từng bước chân của tôi vang lên trên nền gạch lạnh lẽo, như một lời hẹn ước với chính mình rằng tôi sẽ không để mẹ chồng làm tổn thương mình thêm lần nào nữa.</p>\n<p>Tôi ra ngoài sân, nơi cây cối rợp bóng mát, và bắt đầu suy nghĩ về những gì tôi cần làm.</p>\n<p>Tôi phải tìm cách ngăn mẹ chồng thực hiện âm mưu của bà.</p>\n<p>Đầu tiên, tôi cần phải theo dõi bà, xem bà có những hành động gì khả nghi không.</p>\n<p>Bà thường xuyên đến ngân hàng, và tôi cần phải biết bà đang làm gì ở đó.</p>\n<p>Tôi quyết định sẽ nhờ một người bạn có kinh nghiệm điều tra, để theo dõi hoạt động của bà trong những ngày tới.</p>\n<p>Trong lòng tôi dâng lên một cảm giác hồi hộp và lo lắng, nhưng tôi biết rằng đây là cách duy nhất để bảo vệ tài sản và danh dự của mình.</p>\n<p>Tôi quay vào nhà, cảm giác như một chiến binh chuẩn bị cho trận chiến lớn.</p>\n<p>Trong vòng 24 giờ tới, tôi phải chứng minh quyền sở hữu căn biệt thự trước khi mẹ chồng có bất kỳ hành động nào.</p>\n<p>Quyết tâm ấy như một ngọn lửa cháy rực trong lòng, thúc giục tôi phải hành động ngay.</p>\n<p>Khi tôi nhìn vào gương, tôi thấy một người phụ nữ mạnh mẽ, đầy quyết tâm và không bao giờ chịu khuất phục.</p>\n<p>Tôi sẽ không để ai đánh cắp giấc mơ của mình, ngay cả khi đó là mẹ chồng của tôi.</p>"
    },
    {
      "title": "Chương 7: Mẹ Chồng Đứng Chết Lặng Trước Chủ Nhà",
      "content": "<p>Ánh sáng chói chang từ bóng đèn trong phòng khách biệt thự Gò Vấp khiến tôi cảm thấy như bị dồn vào một cái lồng kính, nơi mà mọi ánh mắt đang chĩa vào tôi như những mũi tên sắc nhọn.</p>\n<p>Các thành viên trong gia đình chồng đều có mặt, không khí nặng nề đến mức tôi có thể nghe thấy tiếng thở nặng nề của chính mình.</p>\n<p>Mẹ chồng, với gương mặt lạnh lùng như một tảng băng, ngồi ngay chính giữa, ánh mắt bà như đang đè nén mọi sự bất mãn xuống từng người trong phòng.</p>\n<p>Tôi hít sâu một hơi, cố gắng giữ bình tĩnh, nhưng trái tim tôi như đang đập loạn xạ, nghe rõ mồn một từng nhịp đập như muốn thoát ra khỏi lồng ngực.</p>\n<p>Đối diện tôi, chồng tôi, Nguyễn Huy, chỉ biết cúi đầu, hai bàn tay nắm chặt lại, không dám nhìn vào mắt tôi.</p>\n<p>“Tôi không cần biết cô là ai, nhưng cô mãi mãi là người ngoài trong gia đình này!” Mẹ chồng lạnh lùng tuyên bố, giọng bà sắc lạnh như dao.</p>\n<p>Câu nói ấy như một cú đấm vào mặt tôi, khiến tôi không khỏi cảm thấy chua xót.</p>\n<p>“Mẹ, con...” Huy mở miệng, nhưng lại nhanh chóng im bặt, như thể đã bị một sức mạnh vô hình nào đó ngăn cản.</p>\n<p>“Im ngay!</p>\n<p>Đừng có bênh vực cô ta!” Mẹ chồng lớn tiếng, đôi tay bà siết chặt lại, từng ngón tay trở nên trắng bệch, phẫn nộ và ghê tởm.</p>\n<p>Tôi không thể chờ thêm nữa, nếu không hành động ngay bây giờ, có lẽ sẽ không còn cơ hội nào khác.</p>\n<p>“Tôi có bằng chứng chứng minh quyền sở hữu căn biệt thự này.” Tôi đứng dậy, giọng nói của tôi vang lên như một lời tuyên bố.</p>\n<p>Ánh mắt của tất cả mọi người đều đổ dồn về phía tôi, sự ngạc nhiên hiện rõ trên khuôn mặt của Huy và các thành viên khác.</p>\n<p>Tôi rút từ trong túi xách ra một chiếc USB nhỏ, ánh mắt tôi kiên định khi nhìn thẳng vào mẹ chồng.</p>\n<p>“Bà có nhớ hôm tôi chuyển nhượng sở hữu căn biệt thự này không?</p>\n<p>Mọi thủ tục đã được hoàn tất và tôi đã có trong tay bản sao kê tài khoản ngân hàng từ Việt Thương Bank.”</p>\n<p>“Cô đang đùa à?</p>\n<p>Cô nghĩ cô có thể lừa được chúng tôi bằng cái vật nhỏ bé đó sao?” Mẹ chồng cười nhạt, nhưng trong ánh mắt của bà có chút lo lắng.</p>\n<p>Tôi không để bà có thời gian phản ứng, ngay lập tức kết nối USB vào laptop trên bàn, màn hình nhấp nháy rồi hiện lên bản sao kê tài khoản ngân hàng với số dư 5 tỷ VNĐ.</p>\n<p>“Bà sẽ thấy, đây là tài khoản của tôi, và số tiền này chính là tiền tôi đã dùng để mua căn biệt thự này.”</p>\n<p>Huy nhìn vào màn hình, vẻ mặt anh dần thay đổi từ ngạc nhiên sang lo lắng.</p>\n<p>“Cô đã làm gì vậy?” Anh hỏi, giọng nói vang lên lạc lõng trong bầu không khí căng thẳng này.</p>\n<p>“Tôi đã giữ lại mọi chứng từ cần thiết, và đây là hợp đồng chuyển nhượng có chữ ký số CA và biên bản niêm phong từ cơ quan điều tra.”</p>\n<p>Tôi rút ra một bản hợp đồng từ túi xách, đặt lên bàn, gương mặt tôi không còn một chút do dự.</p>\n<p>Mẹ chồng nhìn vào bản hợp đồng, sắc mặt bà trở nên tối sầm.</p>\n<p>“Cô không thể làm như vậy!” Bà gầm lên, nhưng giọng nói đã yếu đi, thiếu tự tin.</p>\n<p>Tôi cảm thấy một niềm tự hào dâng trào, nhưng cũng không quên sự quyết liệt trong ánh mắt của mẹ chồng.</p>\n<p>“Tôi không chỉ muốn lấy lại danh dự cho mình, mà còn muốn bảo vệ quyền lợi hợp pháp của mình, và điều này sẽ không thay đổi.”</p>\n<p>“Cô không có quyền làm điều này!” Một người họ hàng lên tiếng, vẻ mặt không thể chấp nhận sự thật.</p>\n<p>“Tôi có quyền, và tôi sẽ chiến đấu để bảo vệ quyền lợi của mình.” Tôi khẳng định, ánh mắt tôi sắc như dao.</p>\n<p>Huy vẫn im lặng, nhưng tôi có thể cảm nhận được sự bối rối của anh.</p>\n<p>“Nếu như các bạn không công nhận quyền sở hữu của tôi, tôi sẽ không ngần ngại đưa vụ việc này ra tòa.”</p>\n<p>Mẹ chồng nhìn tôi, gương mặt bà như biến sắc, từng nét nhăn trên trán bà hiện lên rõ ràng, như thể bà đang đối diện với một cơn ác mộng không thể nào thoát ra.</p>\n<p>Tôi không thể để họ dẫm đạp lên danh dự của mình thêm một lần nào nữa, cuộc chiến này sẽ chỉ có một người chiến thắng, và tôi sẽ là người đó.</p>\n<p>Ánh mắt của tôi vẫn kiên định hướng về phía mẹ chồng, tôi biết rằng cuộc chiến pháp lý này mới chỉ bắt đầu.</p>\n<p>Và tôi, Lê Vân, sẽ không bao giờ lùi bước.</p>"
    },
    {
      "title": "Chương 8: Người Ngoài Chính Là Người Có Quyền Đuổi Tất Cả",
      "content": "<p>Hơi thở của tôi như ngưng lại khi cánh cửa của phòng xử án mở ra.</p>\n<p>Ánh mắt tôi hướng về phía bàn xét xử, nơi ba vị thẩm phán đang ngồi, khuôn mặt nghiêm nghị, không một chút biểu cảm.</p>\n<p>Trong lòng, tôi cảm thấy như có hàng triệu con bướm bay lượn, nhưng tôi không thể để sự lo lắng lấn át lý trí của mình.</p>\n<p>Đây là thời điểm quyết định, phán quyết cuối cùng sẽ xác định số phận của tôi và căn biệt thự Gò Vấp mà tôi đã đấu tranh hết sức để bảo vệ.</p>\n<p>Hội đồng xét xử bắt đầu, và giọng của thẩm phán chủ tọa vang lên như tiếng sét giữa trời quang.</p>\n<p>“Hôm nay, chúng tôi sẽ đưa ra phán quyết trong vụ kiện giữa bà Lê Vân và gia đình ông Nguyễn Văn Hùng.”</p>\n<p>Mọi ánh mắt đều đổ dồn vào tôi, những cái nhìn thách thức từ mẹ chồng, những ánh mắt đầy nghi ngờ từ các thành viên trong gia đình chồng.</p>\n<p>Tôi có thể cảm nhận được sự căng thẳng trong không khí, như một sợi dây đàn đang được kéo căng đến mức tối đa.</p>\n<p>Trước khi thẩm phán đưa ra phán quyết, luật sư của tôi, bà Hạnh, đã đứng lên, giọng nói chắc nịch và tự tin.</p>\n<p>“Thưa hội đồng xét xử, chúng tôi đã cung cấp đầy đủ bằng chứng chứng minh quyền sở hữu hợp pháp của bà Lê Vân đối với căn biệt thự tại Gò Vấp.”</p>\n<p>Bà Hạnh giơ cao bản sao kê tài khoản ngân hàng Việt Thương Bank, nơi thể hiện số dư 5 tỷ VNĐ, và hợp đồng chuyển nhượng có chữ ký số CA.</p>\n<p>“Đây là những tài liệu không thể chối cãi, xác nhận rằng căn biệt thự này thuộc quyền sở hữu của bà Lê Vân.”</p>\n<p>Những ánh mắt bắt đầu chuyển từ sự hoài nghi sang sự ngỡ ngàng.</p>\n<p>Bà Hạnh tiếp tục: “Ngoài ra, chúng tôi còn có biên bản niêm phong từ cơ quan điều tra, khẳng định tính hợp lệ của các tài liệu này.”</p>\n<p>Mẹ chồng tôi tái mặt, bàn tay bà siết chặt lại, có thể thấy rõ những khớp tay nổi lên như những đường chỉ hằn sâu.</p>\n<p>Bà Hạnh không dừng lại, bà nhấn mạnh từng từ: “Bà Lê Vân đã bỏ ra công sức và tài chính để sở hữu căn biệt thự này, và việc gia đình ông Hùng cố gắng chiếm đoạt tài sản là vi phạm pháp luật.”</p>\n<p>Hội trường im phăng phắc, chỉ còn tiếng kim đồng hồ tích tắc trên tường.</p>\n<p>Thẩm phán chủ tọa gật đầu, có vẻ ông đã bị thuyết phục bởi những chứng cứ rõ ràng mà chúng tôi đưa ra.</p>\n<p>“Được rồi, chúng ta sẽ tạm nghỉ để hội đồng thảo luận trước khi đưa ra phán quyết cuối cùng.”</p>\n<p>Nghe thấy câu nói ấy, tim tôi như ngừng đập.</p>\n<p>Tôi quay sang nhìn chồng, nhưng anh chỉ cúi đầu, không dám nhìn thẳng vào mắt tôi.</p>\n<p>Tôi cảm thấy nỗi thất vọng tràn ngập, nhưng không thể để điều đó ảnh hưởng đến sự quyết tâm của mình.</p>\n<p>Khoảng thời gian nghỉ ngơi kéo dài như vô tận, từng phút trôi qua như một năm.</p>\n<p>Cuối cùng, khi cánh cửa phòng xử án lại mở ra, không khí trong phòng trở nên đặc quánh, nặng nề.</p>\n<p>Thẩm phán chủ tọa đứng dậy, ánh mắt ông quét qua từng người có mặt trong phòng.</p>\n<p>“Hội đồng xét xử đã đưa ra phán quyết.”</p>\n<p>Gương mặt ông thể hiện sự nghiêm túc, và tôi nín thở, tim đập như trống trận.</p>\n<p>“Sau khi xem xét tất cả các bằng chứng, chúng tôi xác nhận quyền sở hữu hợp pháp của bà Lê Vân đối với căn biệt thự tại Gò Vấp.”</p>\n<p>Câu nói ấy như một tia sáng rực rỡ trong bóng tối, xé toạc bầu không khí ngột ngạt bao trùm.</p>\n<p>Bà Hạnh nở một nụ cười tự hào, còn tôi thì không thể kìm chế được sự xúc động.</p>\n<p>Mẹ chồng tôi như người mất hồn, bà đứng khựng lại, không thể tin vào mắt mình.</p>\n<p>“Hội đồng xét xử cũng ghi nhận rằng mọi hành vi cố tình làm giả giấy tờ hoặc chiếm đoạt tài sản của bà Lê Vân sẽ bị xử lý theo quy định của pháp luật.”</p>\n<p>Từng lời thẩm phán vang lên như tiếng chuông báo thức, đánh thức mọi người khỏi một giấc mơ tồi tệ.</p>\n<p>Tôi đứng dậy, không thể nói nên lời, chỉ biết lặng lẽ nhìn về phía mẹ chồng, ánh mắt tôi như một lời tuyên bố hùng hồn: “Tôi đã thắng.”</p>\n<p>Hội trường trở nên ồn ào, tiếng nói cười và những lời chúc mừng vang lên, nhưng trong lòng tôi chỉ còn lại sự bình yên và mãn nguyện.</p>\n<p>Khi bước ra khỏi phòng xử án, tôi cảm thấy như mình đã vượt qua một cơn bão lớn.</p>\n<p>Mọi sự căng thẳng, lo lắng, và những giọt nước mắt đã tan biến, để lại chỉ là niềm tự hào và sức mạnh.</p>\n<p>Dù biết rằng con đường phía trước sẽ còn nhiều chông gai, nhưng tôi đã chứng minh được rằng, với quyết tâm và lý trí, tôi có thể đứng vững trước mọi thử thách.</p>\n<p>Đó không chỉ là chiến thắng của riêng tôi, mà còn là chiến thắng của những người phụ nữ dám đứng lên khẳng định bản thân và tài sản của mình.</p>\n<p>Tôi quay lại, nhìn về phía căn biệt thự Gò Vấp, nơi chứa đựng bao kỷ niệm và hy vọng.</p>\n<p>“Tôi sẽ bảo vệ nó, như cách tôi đã bảo vệ chính mình.”</p>"
    }
  ],
  "author": "Tiểu Thuyết Việt Nam",
  "seo": {
    "focus_keyword": "biệt thự gò vấp",
    "seo_title": "Mẹ Chồng Gọi Tôi Là Người Ngoài, Sổ Đỏ Biệt Thự Gò Vấp 5 T",
    "seo_description": "Trong mâm giỗ ba chồng, tôi bị mẹ chồng chỉ thẳng mặt gọi là người ngoài và bắt dọn khỏi căn biệt thự Gò Vấp sau bốn năm nhẫn nhịn. Chị chồng cười nhạo tôi dân tỉnh, chồng cúi đầu không nói, còn họ hàng xúm vào ép tôi ký giấy từ bỏ mọi quyền lợi."
  },
  "polished_at": "2026-05-22"
}